chassis/protos/__init__.py
chassis/protos/v1/__init__.py
chassis/protos/v1/model_grpc.py
chassis/protos/v1/model_pb2.py
chassis/protos/v1/model_pb2.pyi
chassisml_protobuf-4.0.0.dist-info/METADATA
chassisml_protobuf-4.0.0.dist-info/WHEEL
chassisml_protobuf-4.0.0.dist-info/top_level.txt
chassisml_protobuf-4.0.0.dist-info/RECORD
