Metadata-Version: 2.1
Name: chassisml-protobuf
Version: 4.0.0
Requires-Dist: protobuf (<5,>=4.21.0)
Requires-Dist: grpclib
